streamlit_datetime_range_picker/__init__.py
streamlit_datetime_range_picker/frontend/build/asset-manifest.json
streamlit_datetime_range_picker/frontend/build/favicon.ico
streamlit_datetime_range_picker/frontend/build/index.html
streamlit_datetime_range_picker/frontend/build/manifest.json
streamlit_datetime_range_picker/frontend/build/robots.txt
streamlit_datetime_range_picker/frontend/build/static/js/main.b37e53d8.js
streamlit_datetime_range_picker/frontend/build/static/js/main.b37e53d8.js.LICENSE.txt
streamlit_datetime_range_picker/frontend/build/static/js/main.b37e53d8.js.map
streamlit_datetime_range_picker-0.0.1.dist-info/LICENSE
streamlit_datetime_range_picker-0.0.1.dist-info/METADATA
streamlit_datetime_range_picker-0.0.1.dist-info/WHEEL
streamlit_datetime_range_picker-0.0.1.dist-info/top_level.txt
streamlit_datetime_range_picker-0.0.1.dist-info/RECORD
