Metadata-Version: 2.1
Name: streamlit-datetime-range-picker
Version: 0.0.1
Summary: this is datetime range picker for streamlit
Home-page: https://github.com/imdreamer2018/streamlit-datetime-range-picker
Author: Yang Qian
Author-email: qian.yang2@thoughtworks.com
Requires-Python: >=3.10
License-File: LICENSE
